MANIFEST.in
readme.rst
setup.cfg
setup.py
terraref/__init__.py
terraref/terrautils/__init__.py
terraref/terrautils/betydb.py
terraref/terrautils/extractors.py
terraref/terrautils/formats.py
terraref/terrautils/gdal.py
terraref/terrautils/geostreams.py
terraref/terrautils/influx.py
terraref/terrautils/lemnatec.py
terraref/terrautils/metadata.py
terraref/terrautils/products.py
terraref/terrautils/sensors.py
terraref/terrautils/spatial.py
terraref_terrautils.egg-info/PKG-INFO
terraref_terrautils.egg-info/SOURCES.txt
terraref_terrautils.egg-info/dependency_links.txt
terraref_terrautils.egg-info/namespace_packages.txt
terraref_terrautils.egg-info/not-zip-safe
terraref_terrautils.egg-info/requires.txt
terraref_terrautils.egg-info/top_level.txt