Metadata-Version: 1.1
Name: terraref-terrautils
Version: 1.1.2
Summary: TERRA-REF workflow utilities
Home-page: https://terraref.org
Author: Max Burnette
Author-email: mburnet2@illinois.edu
License: BSD
Keywords: terraref,clowder,field crop,phenomics,computer vision,remote sensing
Platform: UNKNOWN
Classifier: Development Status :: 4 - Beta
Classifier: Intended Audience :: Science/Research
Classifier: Topic :: Scientific/Engineering :: Bio-Informatics
Classifier: Topic :: Database
Classifier: Topic :: Scientific/Engineering :: GIS
Classifier: Topic :: Utilities
Classifier: License :: OSI Approved :: BSD License
Classifier: Natural Language :: English
Classifier: Programming Language :: Python :: 2.7
